lido_sdk/__init__.py
lido_sdk/config.py
lido_sdk/lido.py
lido_sdk/blstverify/__init__.py
lido_sdk/blstverify/_blst.abi3.so
lido_sdk/blstverify/blst.py
lido_sdk/blstverify/test.py
lido_sdk/blstverify/verifier.py
lido_sdk/contract/__init__.py
lido_sdk/contract/contract.py
lido_sdk/contract/execute_contract.py
lido_sdk/contract/load_contract.py
lido_sdk/contract/abi/Lido.json
lido_sdk/contract/abi/NodeOperatorsRegistry.json
lido_sdk/eth2deposit/__init__.py
lido_sdk/eth2deposit/ssz.py
lido_sdk/eth_multicall/__init__.py
lido_sdk/eth_multicall/multicall.py
lido_sdk/eth_multicall/multicall_address.py
lido_sdk/methods/__init__.py
lido_sdk/methods/keys.py
lido_sdk/methods/operators.py
lido_sdk/methods/stats.py
lido_sdk/methods/typing.py
lido_sdk/network/__init__.py
lido_sdk/network/type.py
lido_sdk_fork-2.5.3.dist-info/LICENSE
lido_sdk_fork-2.5.3.dist-info/METADATA
lido_sdk_fork-2.5.3.dist-info/WHEEL
lido_sdk_fork-2.5.3.dist-info/top_level.txt
lido_sdk_fork-2.5.3.dist-info/RECORD
