Metadata-Version: 2.1
Name: lido-sdk-fork
Version: 2.5.3
Summary: This library consolidates various functions to efficiently load network data for Lido, validate node operator keys and find key duplicates.
Home-page: https://github.com/Sunnight-wj/lido-python-sdk-fork
Author: Lido
Author-email: info@lido.fi
License: MIT
Classifier: License :: OSI Approved :: MIT License
Classifier: Development Status :: 4 - Beta
Classifier: Programming Language :: Python :: 3 :: Only
Classifier: Programming Language :: Python :: 3.7
Classifier: Programming Language :: Python :: 3.8
Classifier: Programming Language :: Python :: 3.9
Requires-Python: >=3.7,<4
License-File: LICENSE
Requires-Dist: multicall (<1,>=0.1.2)
Requires-Dist: web3 (<6,>=5.23.1)
Requires-Dist: ssz (<1,>=0.2.4)
